verbia_cli/__init__.py
verbia_cli/__main__.py
verbia_cli/app.py
verbia_cli/common.py
verbia_cli/config.py
verbia_cli/vocabulary.py
verbia_cli/vocabulary_settings.py
verbia_cli/sqlite/__init__.py
verbia_cli/sqlite/entry_storage.py
verbia_cli/sqlite/model.py
verbia_cli/sqlite/vocabulary_settings_storage.py
verbia_cli/sub_commands/__init__.py
verbia_cli/sub_commands/config.py
verbia_cli/sub_commands/vocabulary.py
verbia_cli/sub_commands/word.py
verbia_cli-0.1.1.dist-info/METADATA
verbia_cli-0.1.1.dist-info/WHEEL
verbia_cli-0.1.1.dist-info/entry_points.txt
verbia_cli-0.1.1.dist-info/RECORD
