Metadata-Version: 2.4
Name: verbia-cli
Version: 0.1.1
Requires-Python: >=3.12
Requires-Dist: aiosqlite>=0.20.0
Requires-Dist: inquirerpy>=0.3.4
Requires-Dist: langcodes>=3.5.0
Requires-Dist: loguru>=0.7.2
Requires-Dist: readchar>=4.2.1
Requires-Dist: rich>=13.9.4
Requires-Dist: sqlalchemy>=2.0.36
Requires-Dist: sqlmodel>=0.0.22
Requires-Dist: typer>=0.14.0
Requires-Dist: verbia-core>=0.1.2
